{
  "$schema": "https://developer.microsoft.com/json-schemas/fabric/item/report/definition/visualContainer/2.7.0/schema.json",
  "name": "e9a5b668791759a03469",
  "position": {
    "x": 1104,
    "y": 84,
    "z": 7000,
    "height": 130,
    "width": 256,
    "tabOrder": 7000
  },
  "visual": {
    "visualType": "image",
    "objects": {
      "general": [
        {
          "properties": {
            "imageUrl": {
              "expr": {
                "ResourcePackageItem": {
                  "PackageName": "RegisteredResources",
                  "PackageType": 1,
                  "ItemName": "Asset_7@4x09137802997652145.png"
                }
              }
            }
          }
        }
      ]
    },
    "visualContainerObjects": {
      "lockAspect": [
        {
          "properties": {
            "show": {
              "expr": {
                "Literal": {
                  "Value": "false"
                }
              }
            }
          }
        }
      ]
    },
    "drillFilterOtherVisuals": true
  },
  "howCreated": "InsertVisualButton"
}